{"data":{"Year":[2010,2010,2010,2014,2010,2010],"seriesdescription":["SG_REG_BRTH","SG_REG_BRTH","SG_REG_BRTH","SG_REG_BRTH","SG_REG_BRTH","SG_REG_BRTH"],"area":["BI","BI","BI","BI","BI","BI"],"sex":["F","M","_T","_T","_T","_T"],"age":["Y0T4","Y0T4","Y0T4","Y0T4","Y0T4","Y0T4"],"urbanisation":["_T","_T","_T","_T","U","R"],"education-level":["_T","_T","_T","_T","_T","_T"],"unit":[null,null,null,null,null,null],"scale":["1","1","1","1","1","1"],"Value":[75.2,74.9,75.2,76.0,86.6,74.1]},"edges":{"From":["seriesdescription","area","sex","age","urbanisation","education-level"],"To":["area","sex","age","urbanisation","education-level","scale"]}}