{"data":{"Year":[2010,2011,2012,2013,2014,2015,2016,2017,2010,2011,2012,2013,2014,2015,2016,2017,2018,2010,2011,2012,2013,2014,2015,2016,2017,2010,2011,2012,2013,2014,2015,2016,2017,2018,2010,2011,2012,2013,2014,2015,2016,2017,2010,2011,2012,2013,2014,2015,2016,2017,2018],"seriesdescription":["D47","D47","D47","D47","D47","D47","D47","D47","D47","D47","D47","D47","D47","D47","D47","D47","D47","D47","D47","D47","D47","D47","D47","D47","D47","D47","D47","D47","D47","D47","D47","D47","D47","D47","D47","D47","D47","D47","D47","D47","D47","D47","D47","D47","D47","D47","D47","D47","D47","D47","D47"],"area":["BI","BI","BI","BI","BI","BI","BI","BI","BI","BI","BI","BI","BI","BI","BI","BI","BI","BI","BI","BI","BI","BI","BI","BI","BI","BI","BI","BI","BI","BI","BI","BI","BI","BI","BI","BI","BI","BI","BI","BI","BI","BI","BI","BI","BI","BI","BI","BI","BI","BI","BI"],"sex":["F","F","F","F","F","F","F","F","F","F","F","F","F","F","F","F","F","M","M","M","M","M","M","M","M","M","M","M","M","M","M","M","M","M","_T","_T","_T","_T","_T","_T","_T","_T","_T","_T","_T","_T","_T","_T","_T","_T","_T"],"age":["_T","_T","_T","_T","_T","_T","_T","_T","_T","_T","_T","_T","_T","_T","_T","_T","_T","_T","_T","_T","_T","_T","_T","_T","_T","_T","_T","_T","_T","_T","_T","_T","_T","_T","_T","_T","_T","_T","_T","_T","_T","_T","_T","_T","_T","_T","_T","_T","_T","_T","_T"],"urbanisation":["_T","_T","_T","_T","_T","_T","_T","_T","_T","_T","_T","_T","_T","_T","_T","_T","_T","_T","_T","_T","_T","_T","_T","_T","_T","_T","_T","_T","_T","_T","_T","_T","_T","_T","_T","_T","_T","_T","_T","_T","_T","_T","_T","_T","_T","_T","_T","_T","_T","_T","_T"],"education-level":["ISCED97_1","ISCED97_1","ISCED97_1","ISCED97_1","ISCED97_1","ISCED97_1","ISCED97_1","ISCED97_1","ISCED97_2","ISCED97_2","ISCED97_2","ISCED97_2","ISCED97_2","ISCED97_2","ISCED97_2","ISCED97_2","AGG_3_4","ISCED97_1","ISCED97_1","ISCED97_1","ISCED97_1","ISCED97_1","ISCED97_1","ISCED97_1","ISCED97_1","ISCED97_2","ISCED97_2","ISCED97_2","ISCED97_2","ISCED97_2","ISCED97_2","ISCED97_2","ISCED97_2","AGG_3_4","ISCED97_1","ISCED97_1","ISCED97_1","ISCED97_1","ISCED97_1","ISCED97_1","ISCED97_1","ISCED97_1","ISCED97_2","ISCED97_2","ISCED97_2","ISCED97_2","ISCED97_2","ISCED97_2","ISCED97_2","ISCED97_2","AGG_3_4"],"unit":["Percent","Percent","Percent","Percent","Percent","Percent","Percent","Percent","Percent","Percent","Percent","Percent","Percent","Percent","Percent","Percent","Percent","Percent","Percent","Percent","Percent","Percent","Percent","Percent","Percent","Percent","Percent","Percent","Percent","Percent","Percent","Percent","Percent","Percent","Percent","Percent","Percent","Percent","Percent","Percent","Percent","Percent","Percent","Percent","Percent","Percent","Percent","Percent","Percent","Percent","Percent"],"TIME_DETAIL":["2010","2011","2012","2013","2014","2015","2016","2017","2010","2011","2012","2013","2014","2015","2016","2017","2018","2010","2011","2012","2013","2014","2015","2016","2017","2010","2011","2012","2013","2014","2015","2016","2017","2018","2010","2011","2012","2013","2014","2015","2016","2017","2010","2011","2012","2013","2014","2015","2016","2017","2018"],"Value":[26.5,30.0,34.1,40.0,40.3,39.9,35.7,40.3,8.5,10.7,10.7,13.3,15.8,21.8,25.1,29.3,29.6,33.5,37.1,39.8,44.4,41.9,38.7,32.3,36.1,13.4,16.6,18.0,20.4,22.8,28.8,30.2,31.6,29.0,30.1,33.6,37.0,42.3,41.1,39.3,33.9,44.5,11.0,13.7,14.4,16.9,19.4,25.4,27.7,26.9,29.3]},"edges":{"From":["seriesdescription","area","sex","age","urbanisation","education-level","unit"],"To":["area","sex","age","urbanisation","education-level","unit","TIME_DETAIL"]}}